indicnlp/__init__.py
indicnlp/common.py
indicnlp/langinfo.py
indicnlp/loader.py
indicnlp/version.py
indicnlp/cli/__init__.py
indicnlp/cli/cliparser.py
indicnlp/morph/__init__.py
indicnlp/morph/unsupervised_morph.py
indicnlp/normalize/__init__.py
indicnlp/normalize/indic_normalize.py
indicnlp/script/__init__.py
indicnlp/script/english_script.py
indicnlp/script/indic_scripts.py
indicnlp/script/phonetic_sim.py
indicnlp/syllable/__init__.py
indicnlp/syllable/syllabifier.py
indicnlp/test/__init__.py
indicnlp/test/unit/__init__.py
indicnlp/tokenize/__init__.py
indicnlp/tokenize/indic_detokenize.py
indicnlp/tokenize/indic_tokenize.py
indicnlp/tokenize/sentence_tokenize.py
indicnlp/transliterate/__init__.py
indicnlp/transliterate/acronym_transliterator.py
indicnlp/transliterate/script_unifier.py
indicnlp/transliterate/sinhala_transliterator.py
indicnlp/transliterate/unicode_transliterate.py
indic_nlp_library-0.92.dist-info/LICENSE
indic_nlp_library-0.92.dist-info/METADATA
indic_nlp_library-0.92.dist-info/WHEEL
indic_nlp_library-0.92.dist-info/top_level.txt
indic_nlp_library-0.92.dist-info/RECORD
