Metadata-Version: 2.1
Name: indic-nlp-library
Version: 0.92
Summary: The goal of the Indic NLP Library is to build Python based libraries for common text processing and Natural Language Processing in Indian languages.
Home-page: https://github.com/anoopkunchukuttan/indic_nlp_library
Download-URL: https://github.com/anoopkunchukuttan/indic_nlp_library/archive/master.zip
Author: Anoop Kunchukuttan
Author-email: anoop.kunchukuttan@gmail.com
License: MIT
Classifier: Programming Language :: Python :: 3
Classifier: License :: OSI Approved :: MIT License
Classifier: Operating System :: OS Independent
Requires-Python: >=3.5
License-File: LICENSE
